{
  "total_solved": 238,
  "easy_solved": 102,
  "medium_solved": 87,
  "hard_solved": 49,
  "current_streak": 1,
  "max_streak": 23,
  "last_solved": "2025-12-02",
  "favorite_topics": [
    "Array",
    "String",
    "Dynamic Programming",
    "Tree"
  ],
  "recent_problems": [
    {
      "name": "Dynamic Programming",
      "difficulty": "Medium",
      "date": "2025-12-02"
    },
    {
      "name": "DFS Traversal",
      "difficulty": "Easy",
      "date": "2025-11-30"
    },
    {
      "name": "Quick Sort",
      "difficulty": "Hard",
      "date": "2025-11-28"
    },
    {
      "name": "Backtracking",
      "difficulty": "Medium",
      "date": "2025-11-27"
    },
    {
      "name": "Backtracking",
      "difficulty": "Medium",
      "date": "2025-11-26"
    }
  ]
}