{
  "total_solved": 208,
  "easy_solved": 95,
  "medium_solved": 77,
  "hard_solved": 36,
  "current_streak": 6,
  "max_streak": 23,
  "last_solved": "2025-10-20",
  "favorite_topics": [
    "Array",
    "String",
    "Dynamic Programming",
    "Tree"
  ],
  "recent_problems": [
    {
      "name": "Greedy Algorithm",
      "difficulty": "Easy",
      "date": "2025-10-20"
    },
    {
      "name": "Quick Sort",
      "difficulty": "Hard",
      "date": "2025-10-19"
    },
    {
      "name": "Dynamic Programming",
      "difficulty": "Hard",
      "date": "2025-10-18"
    },
    {
      "name": "Two Pointers",
      "difficulty": "Easy",
      "date": "2025-10-16"
    },
    {
      "name": "Backtracking",
      "difficulty": "Easy",
      "date": "2025-10-15"
    }
  ]
}